LICENSE.txt
MANIFEST.in
README.rst
setup.cfg
setup.py
rapidsms_twilio.egg-info/PKG-INFO
rapidsms_twilio.egg-info/SOURCES.txt
rapidsms_twilio.egg-info/dependency_links.txt
rapidsms_twilio.egg-info/requires.txt
rapidsms_twilio.egg-info/top_level.txt
rtwilio/__init__.py
rtwilio/admin.py
rtwilio/forms.py
rtwilio/models.py
rtwilio/outgoing.py
rtwilio/urls.py
rtwilio/views.py
rtwilio/migrations/0001_initial.py
rtwilio/migrations/__init__.py
rtwilio/tests/__init__.py
rtwilio/tests/test_forms.py
rtwilio/tests/test_outgoing.py
rtwilio/tests/test_views.py
rtwilio/tests/urls.py